boltzmann/__init__.py
boltzmann/config.py
boltzmann/data.py
boltzmann/data_generator.py
boltzmann/model.py
boltzmann/pipeline.py
boltzmann/preprocessor.py
boltzmann/project.py
boltzmann/run_utils.py
boltzmann/tester.py
boltzmann/utils.py
boltzmann/visualization.py
boltzmann9-0.1.0.dist-info/licenses/LICENSE
templates/config.py
templates/synthetic_generator.py
boltzmann9-0.1.0.dist-info/METADATA
boltzmann9-0.1.0.dist-info/WHEEL
boltzmann9-0.1.0.dist-info/entry_points.txt
boltzmann9-0.1.0.dist-info/top_level.txt
boltzmann9-0.1.0.dist-info/RECORD
